ingress/__init__.py
ingress/apps.py
ingress/models.py
ingress/querysets.py
ingress/settings.py
ingress/urls.py
ingress/views.py
ingress/consumer/__init__.py
ingress/consumer/base.py
ingress/management/__init__.py
ingress/management/commands/__init__.py
ingress/management/commands/activate_collection.py
ingress/management/commands/add_collection.py
ingress/management/commands/clean_consumed_messages.py
ingress/management/commands/consume.py
ingress/management/commands/deactivate_collection.py
ingress/management/commands/disable_consumer.py
ingress/management/commands/enable_consumer.py
ingress/management/commands/list_collections.py
ingress/management/commands/redo_failed_ingress_messages.py
ingress/management/commands/remove_collection.py
ingress/management/commands/remove_failed_messages.py
ingress/management/commands/show_failed_message.py
ingress/migrations/0001_initial.py
ingress/migrations/0002_auto_20201104_1740.py
ingress/migrations/0003_failedingressqueue.py
ingress/migrations/0004_auto_20201109_1649.py
ingress/migrations/0005_auto_20201109_2132.py
ingress/migrations/0006_endpoint_parser_enabled.py
ingress/migrations/0007_auto_20210315_1451.py
ingress/migrations/0008_auto_20210315_1454.py
ingress/migrations/0009_auto_20210315_1454.py
ingress/migrations/0010_auto_20210317_1938.py
ingress/migrations/__init__.py
datapunt_data_ingress-2.3.0.dist-info/LICENSE
datapunt_data_ingress-2.3.0.dist-info/METADATA
datapunt_data_ingress-2.3.0.dist-info/WHEEL
datapunt_data_ingress-2.3.0.dist-info/top_level.txt
datapunt_data_ingress-2.3.0.dist-info/RECORD
